pdf2pptx/__init__.py
pdf2pptx/cli.py
pdf2pptx-1.0.5.dist-info/LICENSE
pdf2pptx-1.0.5.dist-info/METADATA
pdf2pptx-1.0.5.dist-info/WHEEL
pdf2pptx-1.0.5.dist-info/entry_points.txt
pdf2pptx-1.0.5.dist-info/top_level.txt
pdf2pptx-1.0.5.dist-info/RECORD
