Metadata-Version: 2.1
Name: pdf2pptx
Version: 1.0.5
Summary: Utility to convert a PDF slideshow to Powerpoint PPTX.
Home-page: https://github.com/kevinmcguinness/pdf2pptx
Author: Kevin McGuinness
Author-email: kevin.mcguinness@gmail.com
License: MIT
Platform: UNKNOWN
Classifier: Development Status :: 4 - Beta
Classifier: Programming Language :: Python
Classifier: Programming Language :: Python :: 3
Classifier: Programming Language :: Python :: 3.6
Classifier: Environment :: Console
Classifier: License :: OSI Approved :: MIT License
Classifier: Topic :: Utilities
Classifier: Topic :: Multimedia :: Graphics :: Presentation
